MANIFEST.in
README.md
setup.cfg
setup.py
diffusion_device/__init__.py
diffusion_device/basis_generate.py
diffusion_device/compute_profiles_c.py
diffusion_device/compute_profiles_py.py
diffusion_device/display_data.py
diffusion_device/json_info_list.py
diffusion_device/keys.py
diffusion_device/myJSONEncoder.py
diffusion_device/old_fitting.py
diffusion_device/origin_solver.py
diffusion_device/process_data.py
diffusion_device/profile.py
diffusion_device/profiles_fitting.py
diffusion_device.egg-info/PKG-INFO
diffusion_device.egg-info/SOURCES.txt
diffusion_device.egg-info/dependency_links.txt
diffusion_device.egg-info/not-zip-safe
diffusion_device.egg-info/requires.txt
diffusion_device.egg-info/top_level.txt
diffusion_device/data_type/__init__.py
diffusion_device/data_type/images_files.py
diffusion_device/data_type/multi_pos_image.py
diffusion_device/data_type/multi_pos_scan.py
diffusion_device/data_type/scans_files.py
diffusion_device/data_type/single_pos_image.py
diffusion_device/data_type/single_pos_scan.py
diffusion_device/data_type/stack_multi_pos_image.py
diffusion_device/tests/__init__.py
diffusion_device/tests/test.py
diffusion_device/tests/test_data/.DS_Store
diffusion_device/tests/test_data/100pM_RNAseA488_20mM_Pi_200uM_EDTA_pH8_0p1%_Tween_400uW_-100ulh_200_steps_5s_5_steps.csv
diffusion_device/tests/test_data/100pM_RNAseA488_20mM_Pi_200uM_EDTA_pH8_0p1%_Tween_400uW_-100ulh_200_steps_5s_5_steps_metadata.json
diffusion_device/tests/test_data/10pM_RNAseA488_20mM_Pi_200uM_EDTA_pH8_0p1%_Tween_400uW_-100ulh_200_steps_10s_9_steps.csv
diffusion_device/tests/test_data/10pM_RNAseA488_20mM_Pi_200uM_EDTA_pH8_0p1%_Tween_400uW_-100ulh_200_steps_10s_9_steps_metadata.json
diffusion_device/tests/test_data/1tf_001tweentico75_100ulhr.tif
diffusion_device/tests/test_data/1tf_001tweentico75_100ulhr_Metadata.json
diffusion_device/tests/test_data/327.68ul-h-50um device.tif
diffusion_device/tests/test_data/327.68ul-h-50um device_Metadata.json
diffusion_device/tests/test_data/Brightim900ulph.tif
diffusion_device/tests/test_data/Brightim900ulph_Metadata.json
diffusion_device/tests/test_data/Brightim900ulph_fitSettings.json
diffusion_device/tests/test_data/M4-5.tif
diffusion_device/tests/test_data/M4-5_metadata.json
