Metadata-Version: 2.1
Name: diffusion-device
Version: 1.0.0
Summary: Image processing on diffusion device images
Home-page: https://github.com/impact27/diffusion_device
Author: Quentin Peter
Author-email: qaep2@cam.ac.uk
License: GPl v3
Keywords: sizing microfluidics
Platform: UNKNOWN
Classifier: Development Status :: 5 - Production/Stable
Classifier: License :: OSI Approved :: GNU General Public License v3 or later (GPLv3+)
Classifier: Programming Language :: Python :: 3 :: Only
Classifier: Topic :: Scientific/Engineering
